kiarina/lib/google/auth/__init__.py
kiarina/lib/google/auth/_settings.py
kiarina/lib/google/auth/py.typed
kiarina/lib/google/auth/_helpers/__init__.py
kiarina/lib/google/auth/_helpers/get_credentials.py
kiarina/lib/google/auth/_helpers/get_self_signed_jwt.py
kiarina/lib/google/auth/_types/__init__.py
kiarina/lib/google/auth/_types/credentials.py
kiarina/lib/google/auth/_types/credentials_cache.py
kiarina/lib/google/auth/_utils/__init__.py
kiarina/lib/google/auth/_utils/get_default_credentials.py
kiarina/lib/google/auth/_utils/get_service_account_credentials.py
kiarina/lib/google/auth/_utils/get_user_account_credentials.py
kiarina_lib_google_auth-1.35.0.dist-info/METADATA
kiarina_lib_google_auth-1.35.0.dist-info/WHEEL
kiarina_lib_google_auth-1.35.0.dist-info/RECORD
